imgDedup/__init__.py
imgDedup/config.py
imgDedup/scripts/__init__.py
imgDedup/scripts/dedupCli.py
imgDedup/tools/__init__.py
imgDedup/tools/imageFingerprint.py
imgDedup/utils/__init__.py
imgDedup/utils/deduplication.py
imgdedup-1.0.0.dist-info/licenses/LICENSE
imgdedup-1.0.0.dist-info/METADATA
imgdedup-1.0.0.dist-info/WHEEL
imgdedup-1.0.0.dist-info/entry_points.txt
imgdedup-1.0.0.dist-info/top_level.txt
imgdedup-1.0.0.dist-info/RECORD
