Metadata-Version: 2.4
Name: imgDedup
Version: 1.0.0
Summary: 图像去重工具包.
Classifier: Programming Language :: Python :: 3
Classifier: License :: OSI Approved :: Apache Software License
Requires-Python: >=3.11
License-File: LICENSE
Requires-Dist: prettytable
Requires-Dist: imagehash
Requires-Dist: Pillow
Requires-Dist: tqdm
Requires-Dist: numpy
Requires-Dist: loguru
Dynamic: license-file
